setup.cfg
setup.py
drf_fcm/__init__.py
drf_fcm/admin.py
drf_fcm/apps.py
drf_fcm/fcm.py
drf_fcm/models.py
drf_fcm/serializers.py
drf_fcm/settings.py
drf_fcm/tests.py
drf_fcm/urls.py
drf_fcm/views.py
drf_fcm.egg-info/PKG-INFO
drf_fcm.egg-info/SOURCES.txt
drf_fcm.egg-info/dependency_links.txt
drf_fcm.egg-info/requires.txt
drf_fcm.egg-info/top_level.txt
drf_fcm/migrations/0001_initial.py
drf_fcm/migrations/0002_auto_20170316_1411.py
drf_fcm/migrations/0003_auto_20170320_0421.py
drf_fcm/migrations/0004_auto_20170320_0429.py
drf_fcm/migrations/0005_auto_20170320_0502.py
drf_fcm/migrations/__init__.py