Metadata-Version: 1.0
Name: drf-fcm
Version: 0.4.3
Summary: Firebase Cloud Messaging Server in Django Rest FrameWork
Home-page: https://github.com/naviens/django-fcm
Author: Naveen Subramani
Author-email: naviensubramani@gmail.com
License: UNKNOWN
Keywords: gcm,fcm,django-fcm,drf-fcm,django-gcm
Platform: UNKNOWN
